<apam xmlns="fr.imag.adele.apam" xmlns:ipojo="org.apache.felix.ipojo"
	xmlns:xsi="http://www.w3.org/2001/XMLSchema-instance"
	xsi:schemaLocation="fr.imag.adele.apam http://repository-apam.forge.cloudbees.com/release/schema/ApamCore.xsd
                          org.apache.felix.ipojo http://felix.apache.org/ipojo/schemas/CURRENT/core.xsd">

	<implementation name="EnoceanKeyCardSensorImpl"
		classname="appsgate.lig.keycard.sensor.enocean.impl.EnoceanKeyCardSensorImpl" specification="CoreKeyCardSensorSpec" push="notifyChanges">
		<callback onInit="newInst" onRemove="deleteInst" />
		
		<relation field="enoceanProxy" resolve="exist" />
		
		<definition name="deviceName" 	 type="string" default="Unknown" 		field="sensorName"/>
		<definition name="deviceId"   	 type="string" default="000000"		    field="sensorId"/>
		<definition name="deviceType" 	 type="string" default="EnOcean_DEVICE" field="sensoreType"/>
		<definition name="userType"	  	 type="string" default="4" 			    field="userType"/>
		<definition name="status"	  	 type="string" default="2" 			    field="status" 		  method="statusChanged"/>
		<definition name="isPaired"   	 type="string" default="false" 		    field="isPaired" 	  method="isPairedChanged"/>
		<definition name="currentStatus" type="string" default="false"		    field="currentStatus" method="currentStatusChanged"/>
		<definition name="signal"		 type="string" default="0" 		  	  field="signal" 		method="signalChanged"/>
		
	</implementation>

</apam>